LICENSE
MANIFEST.in
README.md
setup.py
celery_admin/__init__.py
celery_admin/admin.py
django_celery_admin.egg-info/PKG-INFO
django_celery_admin.egg-info/SOURCES.txt
django_celery_admin.egg-info/dependency_links.txt
django_celery_admin.egg-info/not-zip-safe
django_celery_admin.egg-info/top_level.txt