Metadata-Version: 1.1
Name: django-celery-admin
Version: 0.1
Summary: A django application that lets you kick off periodic celery tasks from the admin.
Home-page: http://github.com/mattcaldwell/django-celery-admin-ext
Author: Matt Caldwell
Author-email: mcaldwel@ngs.org
License: UNKNOWN
Platform: UNKNOWN
Classifier: Development Status :: 4 - Beta
Classifier: Environment :: Web Environment
Classifier: Intended Audience :: Developers
Classifier: License :: OSI Approved :: BSD License
Classifier: Operating System :: OS Independent
Classifier: Programming Language :: Python
Classifier: Framework :: Django
